{
  "properties": [
    {
      "id": 1,
      "ref": "0010",
      "name": "Departamento bueno",
      "squareMeter": "20",
      "street": "El palomao",
      "streetNumber": "980",
      "buildingFloor": "PB",
      "town": "Córdoba",
      "district": "Siquiman",
      "dailyRent": false,
      "monthlyRent": true,
      "annualRent": false,
      "roomsNumber": 4,
      "bathroomsNumber": 2,
      "internet": true,
      "pool": true,
      "kitchen": true,
      "laundryEquipment": true,
      "yard": true,
      "parking": true,
      "disabledAccess": true,
      "kidsBeds": true,
      "images": [
        "https://images.unsplash.com/photo-1502672023488-70e25813eb80?ixlib=rb-4.0.3&ixid=MnwxMjA3fDB8MHxwaG90by1wYWdlfHx8fGVufDB8fHx8&auto=format&fit=crop&w=1064&q=80",
        "https://images.unsplash.com/photo-1493809842364-78817add7ffb?ixlib=rb-4.0.3&ixid=MnwxMjA3fDB8MHxwaG90by1wYWdlfHx8fGVufDB8fHx8&auto=format&fit=crop&w=1470&q=80",
        "https://images.unsplash.com/photo-1512918728675-ed5a9ecdebfd?ixlib=rb-4.0.3&ixid=MnwxMjA3fDB8MHxwaG90by1wYWdlfHx8fGVufDB8fHx8&auto=format&fit=crop&w=1470&q=80",
        "https://images.unsplash.com/photo-1628592102751-ba83b0314276?ixlib=rb-4.0.3&ixid=MnwxMjA3fDB8MHxwaG90by1wYWdlfHx8fGVufDB8fHx8&auto=format&fit=crop&w=1697&q=80",
        "https://images.unsplash.com/photo-1484154218962-a197022b5858?ixlib=rb-4.0.3&ixid=MnwxMjA3fDB8MHxwaG90by1wYWdlfHx8fGVufDB8fHx8&auto=format&fit=crop&w=1474&q=80"
      ],
      "provinceId": 1,
      "propertyTypeId": 2,
      "availabilityStatusId": 1,
      "activityStatusId": 1,
      "bookings": [],
      "payments": [],
      "isActive": true
    },
    {
      "id": 2,
      "ref": "0011",
      "name": "Casa modelo",
      "squareMeter": "20",
      "street": "El venteveo",
      "streetNumber": "500",
      "buildingFloor": "PB",
      "town": "Carlos Paz",
      "district": "Los solares",
      "dailyRent": false,
      "monthlyRent": true,
      "annualRent": false,
      "roomsNumber": 4,
      "bathroomsNumber": 2,
      "internet": true,
      "pool": true,
      "kitchen": true,
      "laundryEquipment": true,
      "yard": true,
      "parking": true,
      "disabledAccess": true,
      "kidsBeds": true,
      "images": [
        "https://images.unsplash.com/photo-1512918728675-ed5a9ecdebfd?ixlib=rb-4.0.3&ixid=MnwxMjA3fDB8MHxwaG90by1wYWdlfHx8fGVufDB8fHx8&auto=format&fit=crop&w=1470&q=80",
        "https://images.unsplash.com/photo-1493809842364-78817add7ffb?ixlib=rb-4.0.3&ixid=MnwxMjA3fDB8MHxwaG90by1wYWdlfHx8fGVufDB8fHx8&auto=format&fit=crop&w=1470&q=80",
        "https://images.unsplash.com/photo-1502672023488-70e25813eb80?ixlib=rb-4.0.3&ixid=MnwxMjA3fDB8MHxwaG90by1wYWdlfHx8fGVufDB8fHx8&auto=format&fit=crop&w=1064&q=80",
        "https://images.unsplash.com/photo-1628592102751-ba83b0314276?ixlib=rb-4.0.3&ixid=MnwxMjA3fDB8MHxwaG90by1wYWdlfHx8fGVufDB8fHx8&auto=format&fit=crop&w=1697&q=80",
        "https://images.unsplash.com/photo-1484154218962-a197022b5858?ixlib=rb-4.0.3&ixid=MnwxMjA3fDB8MHxwaG90by1wYWdlfHx8fGVufDB8fHx8&auto=format&fit=crop&w=1474&q=80"
      ],
      "provinceId": 1,
      "propertyTypeId": 1,
      "availabilityStatusId": 1,
      "activityStatusId": 1,
      "bookings": [],
      "payments": [],
      "isActive": true
    },
    {
      "id": 3,
      "ref": "0012",
      "name": "Nova modelo",
      "squareMeter": "50",
      "street": "Feuaturer",
      "streetNumber": "823",
      "buildingFloor": "PB",
      "town": "Cosquin",
      "district": "La tablada",
      "dailyRent": false,
      "monthlyRent": true,
      "annualRent": false,
      "roomsNumber": 4,
      "bathroomsNumber": 2,
      "internet": true,
      "pool": true,
      "kitchen": true,
      "laundryEquipment": true,
      "yard": true,
      "parking": true,
      "disabledAccess": true,
      "kidsBeds": true,
      "images": [
        "https://images.unsplash.com/photo-1493809842364-78817add7ffb?ixlib=rb-4.0.3&ixid=MnwxMjA3fDB8MHxwaG90by1wYWdlfHx8fGVufDB8fHx8&auto=format&fit=crop&w=1470&q=80",
        "https://images.unsplash.com/photo-1502672023488-70e25813eb80?ixlib=rb-4.0.3&ixid=MnwxMjA3fDB8MHxwaG90by1wYWdlfHx8fGVufDB8fHx8&auto=format&fit=crop&w=1064&q=80",
        "https://images.unsplash.com/photo-1512918728675-ed5a9ecdebfd?ixlib=rb-4.0.3&ixid=MnwxMjA3fDB8MHxwaG90by1wYWdlfHx8fGVufDB8fHx8&auto=format&fit=crop&w=1470&q=80",
        "https://images.unsplash.com/photo-1628592102751-ba83b0314276?ixlib=rb-4.0.3&ixid=MnwxMjA3fDB8MHxwaG90by1wYWdlfHx8fGVufDB8fHx8&auto=format&fit=crop&w=1697&q=80",
        "https://images.unsplash.com/photo-1484154218962-a197022b5858?ixlib=rb-4.0.3&ixid=MnwxMjA3fDB8MHxwaG90by1wYWdlfHx8fGVufDB8fHx8&auto=format&fit=crop&w=1474&q=80"
      ],
      "provinceId": 1,
      "propertyTypeId": 3,
      "availabilityStatusId": 1,
      "activityStatusId": 1,
      "bookings": [],
      "payments": [],
      "isActive": true
    }
  ]
}
